README.txt
setup.cfg
setup.py
collective/__init__.py
collective.pdfLeadImage.egg-info/PKG-INFO
collective.pdfLeadImage.egg-info/SOURCES.txt
collective.pdfLeadImage.egg-info/dependency_links.txt
collective.pdfLeadImage.egg-info/entry_points.txt
collective.pdfLeadImage.egg-info/namespace_packages.txt
collective.pdfLeadImage.egg-info/not-zip-safe
collective.pdfLeadImage.egg-info/paster_plugins.txt
collective.pdfLeadImage.egg-info/requires.txt
collective.pdfLeadImage.egg-info/top_level.txt
collective/pdfLeadImage/__init__.py
collective/pdfLeadImage/async.py
collective/pdfLeadImage/configure.zcml
collective/pdfLeadImage/events.py
collective/pdfLeadImage/tests.py
collective/pdfLeadImage/utils.py
collective/pdfLeadImage/browser/__init__.py
collective/pdfLeadImage/browser/configure.zcml
collective/pdfLeadImage/browser/views.py
docs/HISTORY.txt
docs/INSTALL.txt
docs/LICENSE.GPL
docs/LICENSE.txt