Metadata-Version: 1.0
Name: collective.pdfLeadImage
Version: 0.2
Summary: Automatically creates contentleadimage from pdf cover
Home-page: http://svn.plone.org/svn/collective/
Author: David Jonas
Author-email: david@itsnotthatkind.org
License: GPL
Keywords: plone pdf jpg leadimage
Platform: UNKNOWN
Classifier: Framework :: Plone
Classifier: Programming Language :: Python
